odoo/addons/ssi_service_risk_analysis/README.rst
odoo/addons/ssi_service_risk_analysis/__init__.py
odoo/addons/ssi_service_risk_analysis/__manifest__.py
odoo/addons/ssi_service_risk_analysis/models/__init__.py
odoo/addons/ssi_service_risk_analysis/models/service_contract.py
odoo/addons/ssi_service_risk_analysis/static/description/icon.png
odoo14_addon_ssi_service_risk_analysis-14.0.1.0.0.dist-info/METADATA
odoo14_addon_ssi_service_risk_analysis-14.0.1.0.0.dist-info/WHEEL
odoo14_addon_ssi_service_risk_analysis-14.0.1.0.0.dist-info/top_level.txt
odoo14_addon_ssi_service_risk_analysis-14.0.1.0.0.dist-info/RECORD
